aaclient/__init__.py
aaclient/appl.py
aaclient/_ext.cpython-311-x86_64-linux-gnu.so
aaclient/dtype.py
aaclient/date.py
aaclient/threading.py
aaclient/conf.py
aaclient/util.py
aaclient/test/__init__.py
aaclient/test/test_threading.py
aaclient/test/testdata.pb
aaclient/test/test_conf.py
aaclient/test/test_RH.pb
aaclient/test/test_aa.py
aaclient/test/test_ext.py
aaclient/test/test_util.py
aaclient/test/test_date.py
aaclient/cmd/__init__.py
aaclient/cmd/h5.py
aaclient/cmd/grep.py
aaclient/cmd/get.py
aaclient.libs/libprotobuf-lite-319b9df8.so.8.0.0
aaclient-0.0.5.dist-info/entry_points.txt
aaclient-0.0.5.dist-info/METADATA
aaclient-0.0.5.dist-info/RECORD
aaclient-0.0.5.dist-info/top_level.txt
aaclient-0.0.5.dist-info/WHEEL
aaclient-0.0.5.dist-info/licenses/LICENSE
