Metadata-Version: 2.1
Name: aaclient
Version: 0.0.5
Summary: Tools to query Archiver Appliance and export data
Home-page: https://github.com/mdavidsaver/aaclient
Author: Michael Davidsaver
Author-email: mdavidsaver@gmail.com
License: BSD
Classifier: Programming Language :: Python :: 3
Classifier: Programming Language :: Python :: Implementation :: CPython
Classifier: License :: OSI Approved :: BSD License
Classifier: Intended Audience :: Science/Research
Classifier: Topic :: Scientific/Engineering
Requires-Python: >=3.7
Provides-Extra: hdf5
License-File: LICENSE
